[
  {
    "text": "D605",
    "type": "area-code",
    "lat": 40.7864942,
    "lng": 29.9754291,
    "fszl": -1
  },
  {
    "text": "D615",
    "type": "area-code",
    "lat": 38.95840016486281,
    "lng": 30.088058064732373,
    "fszl": -1
  },
  {
    "text": "D625",
    "type": "area-code",
    "lat": 38.3196762,
    "lng": 29.7388125,
    "fszl": -1
  },
  {
    "text": "D635",
    "type": "area-code",
    "lat": 37.308699,
    "lng": 30.4825267,
    "fszl": -1
  },
  {
    "text": "D650",
    "type": "area-code",
    "lat": 39.99692230190077,
    "lng": 29.98574462817995,
    "fszl": -1
  },
  {
    "text": "D655",
    "type": "area-code",
    "lat": 40.8651655,
    "lng": 31.1677176,
    "fszl": -1
  },
  {
    "text": "D665",
    "type": "area-code",
    "lat": 39.12030053156745,
    "lng": 30.583625656047044,
    "fszl": -1
  },
  {
    "text": "D675",
    "type": "area-code",
    "lat": 38.9228071,
    "lng": 31.0715038,
    "fszl": -1
  },
  {
    "text": "D685",
    "type": "area-code",
    "lat": 37.6749355,
    "lng": 30.6629595,
    "fszl": -1
  },
  {
    "text": "D687",
    "type": "area-code",
    "lat": 37.23034088372551,
    "lng": 31.483087933599858,
    "fszl": -1
  },
  {
    "text": "D695",
    "type": "area-code",
    "lat": 38.506265674308445,
    "lng": 31.523167154101557,
    "fszl": -1
  },
  {
    "text": "D696",
    "type": "area-code",
    "lat": 37.782783609744904,
    "lng": 32.255725037194836,
    "fszl": -1
  }
]